thatscraper/__init__.py
thatscraper/browser.py
thatscraper/common/__init__.py
thatscraper/common/exceptions.py
thatscraper/common/logger.py
thatscraper/data.py
thatscraper/extractor.py
thatscraper-0.2.8.dist-info/LICENSE
thatscraper-0.2.8.dist-info/WHEEL
thatscraper-0.2.8.dist-info/METADATA
thatscraper-0.2.8.dist-info/RECORD
