Metadata-Version: 2.1
Name: thatscraper
Version: 0.2.8
Summary: A selenium adapter for automated actions on browsers.
License: MIT
Author: Vagner Bessa
Requires-Python: >=3.9,<4.0
Classifier: Development Status :: 2 - Pre-Alpha
Classifier: Intended Audience :: Developers
Classifier: License :: OSI Approved :: MIT License
Classifier: Programming Language :: Python :: 3
Classifier: Programming Language :: Python :: 3.9
Classifier: Programming Language :: Python :: 3.10
Classifier: Programming Language :: Python :: 3.11
Classifier: Programming Language :: Python :: 3
Classifier: Topic :: Internet
Requires-Dist: lxml (>=4.9.1,<5.0.0)
Requires-Dist: pandas (>=1.5.0,<2.0.0)
Requires-Dist: polling2 (>=0.5.0,<0.6.0)
Requires-Dist: requests (>=2.28.1,<3.0.0)
Requires-Dist: selenium (>=4.5.0,<5.0.0)
